pyreality/__init__.py
pyreality/pyreality.py
pyreality-0.0.6.dist-info/LICENSE
pyreality-0.0.6.dist-info/METADATA
pyreality-0.0.6.dist-info/WHEEL
pyreality-0.0.6.dist-info/top_level.txt
pyreality-0.0.6.dist-info/RECORD
