Metadata-Version: 2.1
Name: pyreality
Version: 0.0.6
Summary: Create mixed reality visualisations in Jupyter Notebooks
Home-page: https://github.com/tashfeenahmed/pyreality
Author: Tashfeen Ahmed
Author-email: tashfene@gmail.com
License: UNKNOWN
Project-URL: Bug Tracker, https://github.com/tashfeenahmed/pyreality/issues
Platform: UNKNOWN
Classifier: Programming Language :: Python :: 3
Classifier: License :: OSI Approved :: MIT License
Classifier: Operating System :: OS Independent
Requires-Python: >=3.6
License-File: LICENSE
